[{"template": "Heck reaction", "metadata": {"q_value": 1.558337099708539, "visits": 8.283333333333333}, "count": 6}, {"template": "Cyano or imine to amine", "metadata": {"q_value": 1.0029368639044585, "visits": 690.1029782814114}, "count": 683}, {"template": "Dehydration", "metadata": {"q_value": 1.003571439980395, "visits": 568.9078275712369}, "count": 562}, {"template": "Sulfonation", "metadata": {"q_value": 1.001642037232555, "visits": 1227.6834119105736}, "count": 1220}, {"template": "Wittig olefination", "metadata": {"q_value": 1.0022701504877674, "visits": 890.359974507209}, "count": 883}, {"template": "Ester to alcohol", "metadata": {"q_value": 1.0006508298769472, "visits": 3083.6081132347063}, "count": 3075}, {"template": "Nitrile to acid", "metadata": {"q_value": 1.0090091926452913, "visits": 229.98662791308203}, "count": 224}, {"template": "Other deprotections", "metadata": {"q_value": 1.002820880090705, "visits": 718.1431846949781}, "count": 711}, {"template": "Other heteroatom alkylation/arylation", "metadata": {"q_value": 1.0834851787398687, "visits": 29.815958177753515}, "count": 26}, {"template": "Alkene oxidative cleavage", "metadata": {"q_value": 0.00042054825462400913, "visits": 1}, "count": 1}, {"template": "Alcohols to acids", "metadata": {"q_value": 1.0025542825879397, "visits": 792.2422623047763}, "count": 785}, {"template": "Oxidations at nitrogen", "metadata": {"q_value": 1.2023164933404797, "visits": 15.019877344877344}, "count": 12}, {"template": "N-sulfonylation", "metadata": {"q_value": 1.002865335402538, "visits": 707.1275815441628}, "count": 700}, {"template": "Friedel-Crafts reaction", "metadata": {"q_value": 1.0023696715770216, "visits": 853.3171438915253}, "count": 846}, {"template": "Alkyne to alkane", "metadata": {"q_value": 1.009852457029274, "visits": 210.89778463670774}, "count": 205}, {"template": "Acid to acid chloride", "metadata": {"q_value": 1.0008976662491398, "visits": 2238.2867482973497}, "count": 2230}, {"template": "Other protections", "metadata": {"q_value": 1.0016103070028903, "visits": 1251.7029009550902}, "count": 1244}, {"template": "RCO2H protections", "metadata": {"q_value": 1.0011627910909506, "visits": 1730.0281669617393}, "count": 1722}, {"template": "N-substitution with alkyl-X", "metadata": {"q_value": 1.0014903137938498, "visits": 1351.7802491160403}, "count": 1344}, {"template": "N-containing heterocycle formation", "metadata": {"q_value": 1.0010995055551342, "visits": 1829.0840821450884}, "count": 1821}, {"template": "Sonogashira reaction", "metadata": {"q_value": 1.0196097470036953, "visits": 109.2167911671714}, "count": 104}, {"template": "Ketone to alcohol", "metadata": {"q_value": 1.0005366246697134, "visits": 3737.800976954888}, "count": 3729}, {"template": "Oxidations at sulfur", "metadata": {"q_value": 1.009901233971889, "visits": 209.89288267592343}, "count": 204}, {"template": "Grignard reaction", "metadata": {"q_value": 1.0006381621581655, "visits": 3144.6277595991255}, "count": 3136}, {"template": "Other Pd-catalyzed reactions (Negishi,Kumada,etc.)", "metadata": {"q_value": 1.0153855329395984, "visits": 137.4562249260523}, "count": 132}, {"template": "Other functional group addition", "metadata": {"q_value": 1.0002767017208478, "visits": 7239.463140822162}, "count": 7230}, {"template": "Carbamate/carbonate formation", "metadata": {"q_value": 1.0122704033683427, "visits": 170.68012777487093}, "count": 165}, {"template": "Other oxidations", "metadata": {"q_value": 1.0002756719556172, "visits": 7266.466868563598}, "count": 7257}, {"template": "Halogenation", "metadata": {"q_value": 1.000348553513551, "visits": 5749.2323430436745}, "count": 5740}, {"template": "O-containing heterocycle formation", "metadata": {"q_value": 1.002828859981471, "visits": 716.1403658070383}, "count": 709}, {"template": "Alcohol to halide", "metadata": {"q_value": 1.0003413551900104, "visits": 5870.2532058692805}, "count": 5861}, {"template": "S-substitution", "metadata": {"q_value": 1.0010911077990088, "visits": 1843.091742921077}, "count": 1835}, {"template": "Other C-C bond formation", "metadata": {"q_value": 1.0025413001692716, "visits": 796.2473481383213}, "count": 789}, {"template": "N-arylation with Ar-X", "metadata": {"q_value": 1.0011757793601619, "visits": 1711.0170687173002}, "count": 1703}, {"template": "Other organometallic C-C bond formation", "metadata": {"q_value": 1.0010531861795118, "visits": 1909.1270879648662}, "count": 1901}, {"template": "Reductive amination", "metadata": {"q_value": 1.000006669023055, "visits": 299909.1884050286}, "count": 299896}, {"template": "Alkene to alkane", "metadata": {"q_value": 1.00000666633335, "visits": 300030.18880842114}, "count": 300017}, {"template": "Amide to amine reduction", "metadata": {"q_value": 1.000003401406822, "visits": 588007.8616868434}, "count": 587994}, {"template": "O-acylation to ester", "metadata": {"q_value": 1.0000033592217354, "visits": 595391.8741666083}, "count": 595378}, {"template": "NH protections", "metadata": {"q_value": 1.0000066916264334, "visits": 298896.18502146757}, "count": 298883}, {"template": "RSH deprotections", "metadata": {"q_value": 1.000006855301719, "visits": 291760.1608562219}, "count": 291747}, {"template": "O-substitution", "metadata": {"q_value": 1.000006476998559, "visits": 308800.2176210473}, "count": 308787}, {"template": "Alcohols to aldehydes", "metadata": {"q_value": 1.000006814611891, "visits": 293502.16680940386}, "count": 293489}, {"template": "Suzuki coupling", "metadata": {"q_value": 1.0000067301091624, "visits": 297187.17928709113}, "count": 297174}, {"template": "RCO2H deprotections", "metadata": {"q_value": 1.0000033893307259, "visits": 590102.8652434755}, "count": 590089}, {"template": "N-acylation to amide", "metadata": {"q_value": 1.0000011333088539, "visits": 1764760.9607327206}, "count": 1764746}, {"template": "ROH deprotections", "metadata": {"q_value": 1.0000017006123054, "visits": 1176063.5548863239}, "count": 1176049}, {"template": "Other functional group interconversion", "metadata": {"q_value": 1.0000002350797803, "visits": 8507771.236175602}, "count": 8507752}, {"template": "Nitro to amine reduction", "metadata": {"q_value": 1.0000034197094956, "visits": 584860.8563203706}, "count": 584847}, {"template": "NH deprotections", "metadata": {"q_value": 1.0000002638852805, "visits": 7579072.7718317555}, "count": 7579053}, {"template": "Other reductions", "metadata": {"q_value": 1.0000066743644338, "visits": 299669.1876044295}, "count": 299656}, {"template": "Heteroaryl N-alkylation", "metadata": {"q_value": 1.0000033537802133, "visits": 596357.8757877935}, "count": 596344}, {"template": "N-acylation to urea", "metadata": {"q_value": 1.0000068648314684, "visits": 291355.159467066}, "count": 291342}, {"template": "Unassigned", "metadata": {"q_value": 1.0000004471008195, "visits": 4473282.389027898}, "count": 4473266}, {"template": "ROH protections", "metadata": {"q_value": 1.0000068391500305, "visits": 292449.163215077}, "count": 292436}]