{"Other reductions": 10.0, "N-arylation with Ar-X": 10.0, "Unassigned": 10.0, "Reductive amination": 10.0, "Halogenation": 10.0, "O-containing heterocycle formation": 10.0, "Heteroaryl N-alkylation": 10.0, "O-substitution": 10.0, "Alcohol to halide": 10.0, "Alkene oxidative cleavage": 10.0, "RCO2H deprotections": 10.0, "O-sulfonylation": 10.0, "Other functional group interconversion": 10.0, "Friedel-Crafts reaction": 10.0, "NH deprotections": 10.0, "Nitro to amine reduction": 10.0, "Stille reaction": 10.0, "NH protections": 10.0, "Amide to amine reduction": 10.0, "N-acylation to amide": 10.0}